pymsgbus/__init__.py
pymsgbus/asyncio/__init__.py
pymsgbus/asyncio/consumer.py
pymsgbus/asyncio/producer.py
pymsgbus/asyncio/publisher.py
pymsgbus/asyncio/service.py
pymsgbus/asyncio/subscriber.py
pymsgbus/consumer.py
pymsgbus/depends.py
pymsgbus/producer.py
pymsgbus/publisher.py
pymsgbus/service.py
pymsgbus/subscriber.py
pymsgbus-0.4.4.dist-info/METADATA
pymsgbus-0.4.4.dist-info/WHEEL
pymsgbus-0.4.4.dist-info/licenses/LICENSE
pymsgbus-0.4.4.dist-info/RECORD
