Metadata-Version: 2.4
Name: pymsgbus
Version: 0.4.4
Summary: "A python framework for event driven systems"
License: Apache-2.0
License-File: LICENSE
Author: entropy-flux
Author-email: eric.hermosis@gmail.com
Requires-Python: >=3.12,<4.0
Classifier: License :: OSI Approved :: Apache Software License
Classifier: Programming Language :: Python :: 3
Classifier: Programming Language :: Python :: 3.12
Classifier: Programming Language :: Python :: 3.13
Classifier: Programming Language :: Python :: 3.14
